powerschool_alchemy/__init__.py
powerschool_alchemy/db.py
powerschool_alchemy/test.py
powerschool_alchemy/models/Attendance.py
powerschool_alchemy/models/AttendanceCode.py
powerschool_alchemy/models/CC.py
powerschool_alchemy/models/CalendarDay.py
powerschool_alchemy/models/Course.py
powerschool_alchemy/models/CycleDay.py
powerschool_alchemy/models/Guardian.py
powerschool_alchemy/models/GuardianStudent.py
powerschool_alchemy/models/Period.py
powerschool_alchemy/models/School.py
powerschool_alchemy/models/SchoolCourse.py
powerschool_alchemy/models/Section.py
powerschool_alchemy/models/SectionMeeting.py
powerschool_alchemy/models/Student.py
powerschool_alchemy/models/StudentCoreField.py
powerschool_alchemy/models/StudentTest.py
powerschool_alchemy/models/StudentTestScore.py
powerschool_alchemy/models/Teacher.py
powerschool_alchemy/models/Term.py
powerschool_alchemy/models/Test.py
powerschool_alchemy/models/TestScore.py
powerschool_alchemy/models/__init__.py
powerschool_alchemy/models/base.py
powerschool_alchemy-0.0.17.dist-info/DESCRIPTION.rst
powerschool_alchemy-0.0.17.dist-info/METADATA
powerschool_alchemy-0.0.17.dist-info/RECORD
powerschool_alchemy-0.0.17.dist-info/WHEEL
powerschool_alchemy-0.0.17.dist-info/metadata.json
powerschool_alchemy-0.0.17.dist-info/top_level.txt
