Metadata-Version: 2.0
Name: powerschool-alchemy
Version: 0.0.17
Summary: This library allows you to interact with a PowerSchool Database with SQLALchemy, a Python ORM
Home-page: https://github.com/IronCountySchoolDistrict/powerschool-alchemy
Author: Iron County School District
Author-email: data@ironmail.org
License: MIT
Platform: UNKNOWN
Requires-Dist: python-dotenv
Requires-Dist: SQLAlchemy
Requires-Dist: cx-oracle
